grove/__init__.py
grove/adc.py
grove/adc_8chan_12bit.py
grove/grove_12_channel_touch_keypad.py
grove/grove_12_key_cap_i2c_touch_mpr121.py
grove/grove_1wire_thermocouple_amplifier_max31850.py
grove/grove_3_axis_accelerometer_adxl372.py
grove/grove_3_axis_compass_bmm150.py
grove/grove_3_axis_digital_accelerometer.py
grove/grove_4_digit_display.py
grove/grove_6_axis_accel_gyro_bmi088.py
grove/grove_PM2_5_HM3301.py
grove/grove_air_quality_sensor_v1_3.py
grove/grove_button.py
grove/grove_cap_touch_slider_cy8c.py
grove/grove_chainable_rgb_led.py
grove/grove_collision_sensor.py
grove/grove_current_sensor.py
grove/grove_gesture_sensor.py
grove/grove_gpio.py
grove/grove_high_accuracy_temperature.py
grove/grove_i2c_color_sensor_v2.py
grove/grove_i2c_motor_driver.py
grove/grove_i2c_thermocouple_amplifier_mcp9600.py
grove/grove_imu_9dof_icm20600_ak09918.py
grove/grove_led.py
grove/grove_light_sensor_v1_2.py
grove/grove_loudness_sensor.py
grove/grove_mech_keycap.py
grove/grove_mini_pir_motion_sensor.py
grove/grove_moisture_sensor.py
grove/grove_multi_switch.py
grove/grove_oled_display_128x64.py
grove/grove_optical_rotary_encoder.py
grove/grove_piezo_vibration_sensor.py
grove/grove_pwm_buzzer.py
grove/grove_recorder_v3_0.py
grove/grove_relay.py
grove/grove_rotary_angle_sensor.py
grove/grove_round_force_sensor.py
grove/grove_ryb_led_button.py
grove/grove_servo.py
grove/grove_slide_potentiometer.py
grove/grove_sound_sensor.py
grove/grove_step_counter_bma456.py
grove/grove_switch.py
grove/grove_temperature_humidity_bme680.py
grove/grove_temperature_humidity_sensor_sht3x.py
grove/grove_temperature_sensor.py
grove/grove_thumb_joystick.py
grove/grove_tilt_switch.py
grove/grove_time_of_flight_distance.py
grove/grove_touch_sensor.py
grove/grove_ultrasonic_ranger.py
grove/grove_uv_sensor.py
grove/grove_water_sensor.py
grove/grove_ws2813_rgb_led_strip.py
grove/i2c.py
grove/spi.py
grove/uart.py
grove/button/__init__.py
grove/button/button.py
grove/button/button_gpio.py
Seeed_grove.py-0.3.dist-info/LICENSE
Seeed_grove.py-0.3.dist-info/METADATA
Seeed_grove.py-0.3.dist-info/WHEEL
Seeed_grove.py-0.3.dist-info/top_level.txt
Seeed_grove.py-0.3.dist-info/RECORD
