Metadata-Version: 2.1
Name: Seeed-grove.py
Version: 0.3
Summary: Python library for Seeedstudio Grove devices
Home-page: https://github.com/seeed-studio/grove.py
Author: JunJie Chen
Author-email: hansen.chen@seeed.cc
License: MIT
Keywords: grove,Seeed
Platform: UNKNOWN
Classifier: Development Status :: 2 - Pre-Alpha
Classifier: Intended Audience :: Developers
Classifier: License :: OSI Approved :: MIT License
Classifier: Operating System :: POSIX :: Linux
Classifier: Programming Language :: Python :: 2
Classifier: Programming Language :: Python :: 2.7
Classifier: Programming Language :: Python :: 3
Classifier: Programming Language :: Python :: 3.4
Classifier: Programming Language :: Python :: 3.5
Requires-Dist: pyserial
Requires-Dist: smbus2
Requires-Dist: spidev
